finosdk/__init__.py
finosdk/client.py
finosdk/exceptions.py
finosdk_preview-0.0.1a4.dist-info/licenses/LICENSE
finosdk_preview-0.0.1a4.dist-info/METADATA
finosdk_preview-0.0.1a4.dist-info/WHEEL
finosdk_preview-0.0.1a4.dist-info/top_level.txt
finosdk_preview-0.0.1a4.dist-info/RECORD
